auto_base/__init__.py
auto_base/core.py
auto_base-0.1.0.dist-info/licenses/LICENSE
auto_base-0.1.0.dist-info/METADATA
auto_base-0.1.0.dist-info/WHEEL
auto_base-0.1.0.dist-info/top_level.txt
auto_base-0.1.0.dist-info/RECORD
