Metadata-Version: 2.4
Name: auto-base
Version: 0.1.0
Summary: A thin wrapper for autogen library with optional ag2 support
Home-page: https://github.com/yourusername/auto-base
Author: Your Name
Author-email: Your Name <your.email@example.com>
Project-URL: Homepage, https://github.com/yourusername/auto-base
Project-URL: Bug Tracker, https://github.com/yourusername/auto-base/issues
Classifier: Programming Language :: Python :: 3
Classifier: License :: OSI Approved :: MIT License
Classifier: Operating System :: OS Independent
Requires-Python: >=3.6
License-File: LICENSE
Requires-Dist: ag2>=0.1.0
Requires-Dist: autogen>=0.1.0
Dynamic: author
Dynamic: home-page
Dynamic: license-file
Dynamic: requires-python
